berlekamp_messey.cpython-312-darwin.so
app/__init__.py
app/random_test_tool.py
random_sample_tester/__init__.py
random_sample_tester/generate_reports.py
random_sample_tester/random_sample_tester.py
statistical_tests/__init__.py
statistical_tests/statistical_test.py
statistical_tests/statistical_tests/__init__.py
statistical_tests/statistical_tests/binary_rank_test.py
statistical_tests/statistical_tests/block_chi2.py
statistical_tests/statistical_tests/chi2_test.py
statistical_tests/statistical_tests/compression_test.py
statistical_tests/statistical_tests/linear_complexity_test.py
statistical_tests/statistical_tests/longest_run_of_ones.py
statistical_tests/statistical_tests/run_test.py
statistical_tests/statistical_tests/serial_test.py
statistical_tests/statistical_tests/sign_test.py
statistical_tests/statistical_tests/spectral_test.py
tests/__init__.py
tests/utils.py
utils/__init__.py
utils/config_manager.py
utils/data_type.py
utils/exceptions.py
random_test_tool-1.1.0.dist-info/LICENSE
random_test_tool-1.1.0.dist-info/METADATA
random_test_tool-1.1.0.dist-info/WHEEL
random_test_tool-1.1.0.dist-info/entry_points.txt
random_test_tool-1.1.0.dist-info/top_level.txt
random_test_tool-1.1.0.dist-info/RECORD
