Metadata-Version: 2.1
Name: random_test_tool
Version: 1.1.0
Summary: A simple python tool used for validating pseudo random generators output.
Home-page: https://github.com/xmco/random_test_tool/
Author: Antoine Rigoureau
Author-email: antoine.rigoureau@xmco.fr
Classifier: Programming Language :: Python :: 3
Classifier: License :: OSI Approved :: MIT License
Classifier: Operating System :: OS Independent
Requires-Python: >=3.11
License-File: LICENSE
Requires-Dist: numpy >=1.24.2
Requires-Dist: packaging >=23.0
Requires-Dist: pandas >=1.5.3
Requires-Dist: patsy >=0.5.3
Requires-Dist: python-dateutil >=2.8.2
Requires-Dist: pytz >=2023.3
Requires-Dist: scipy >=1.10.1
Requires-Dist: six >=1.16.0
Requires-Dist: statsmodels >=0.13.5
Requires-Dist: tabulate >=0.9.0
Requires-Dist: matplotlib >=3.7.1
Requires-Dist: alive-progress >=3.1.4
Requires-Dist: bitstring >=4.1.3
Requires-Dist: tqdm >=4.66.1
Requires-Dist: plotly >=5.23.0
Requires-Dist: jinja2 >=3.1.4
Requires-Dist: PyYAML >=6.0.1
Requires-Dist: cython >=3.0.11
